think/__init__.py
think/errors.py
think/interpreter.py
think/jupyter_magic.py
think/parser.py
think/parsetab.py
think/py.typed
think/validator.py
think_lang-0.1.9.dist-info/LICENSE
think_lang-0.1.9.dist-info/METADATA
think_lang-0.1.9.dist-info/WHEEL
think_lang-0.1.9.dist-info/top_level.txt
think_lang-0.1.9.dist-info/RECORD
