Metadata-Version: 2.1
Name: think-lang
Version: 0.1.9
Summary: Think - A language for learning computational thinking
Author-email: Lawrence Wilson Gray <lwgray@gmail.com>
License: MIT License
Project-URL: Homepage, https://think-lang.org
Project-URL: Documentation, https://think-lang.readthedocs.io/
Project-URL: Repository, https://github.com/lwgray/think.git
Project-URL: Issues, https://github.com/lwgray/think/issues
Keywords: education,programming,computational thinking
Classifier: Programming Language :: Python :: 3
Classifier: License :: OSI Approved :: MIT License
Classifier: Operating System :: OS Independent
Requires-Python: >=3.7
License-File: LICENSE
Requires-Dist: ply
Requires-Dist: ipython
Requires-Dist: jupyter
